ie_pandas/DataFrame.py
ie_pandas/__init__.py
ie_pandas-0.0.2.dist-info/METADATA
ie_pandas-0.0.2.dist-info/WHEEL
ie_pandas-0.0.2.dist-info/license.txt
ie_pandas-0.0.2.dist-info/top_level.txt
ie_pandas-0.0.2.dist-info/RECORD
