Metadata-Version: 2.1
Name: ie-pandas
Version: 0.0.2
Summary: A simple implementation of dataframe functionality
Home-page: UNKNOWN
Author: group_c
License: MIT
Platform: UNKNOWN
Requires-Dist: numpy (>=1.16)
Requires-Dist: matplotlib (>=3.0.2)
Provides-Extra: dev
Requires-Dist: black ; extra == 'dev'
Requires-Dist: pytest (>=4.2) ; extra == 'dev'
Requires-Dist: pytest-cov (>=2.6) ; extra == 'dev'
